syncfile/__init__.py
syncfile/__main__.py
syncfile/client.py
syncfile/down.py
syncfile/server.py
syncfile/utils.py
syncfile-0.3.1.2.dist-info/METADATA
syncfile-0.3.1.2.dist-info/WHEEL
syncfile-0.3.1.2.dist-info/licenses/LICENCE
syncfile-0.3.1.2.dist-info/RECORD
