Metadata-Version: 2.3
Name: syncfile
Version: 0.3.1.2
Summary: Simple file synchronization service (clients in the same package)
Project-URL: Homepage, https://github.com/ECSDevs/FileSync
Project-URL: Bug Tracker, https://github.com/ECSDevs/FileSync/issues
Project-URL: Support Me, https://afdian.net/a/Syncfile_transfer_tool
Author-email: ECSDevs <psbash@groupmail.com>
Maintainer-email: originalFactor <2438926613@qq.com>
License:                     GNU GENERAL PUBLIC LICENSE
License-File: LICENCE
Classifier: Development Status :: 4 - Beta
Classifier: License :: OSI Approved :: GNU General Public License v3 (GPLv3)
Classifier: Operating System :: OS Independent
Classifier: Programming Language :: Python :: 3
Requires-Python: >=3.8
Requires-Dist: dnspython
Requires-Dist: httpx
Requires-Dist: pydantic
